patroller_util/__init__.py
patroller_util/attribute.py
patroller-0.1a1.dist-info/METADATA
patroller-0.1a1.dist-info/WHEEL
patroller-0.1a1.dist-info/top_level.txt
patroller-0.1a1.dist-info/zip-safe
patroller-0.1a1.dist-info/RECORD
