Metadata-Version: 2.1
Name: patroller
Version: 0.1a1
Summary: System Inspection Kits
Home-page: https://github.com/bondbox/patroller/
Author: Mingzhe Zou
Author-email: zoumingzhe@outlook.com
License: GPLv2
Project-URL: Source Code, https://github.com/bondbox/patroller/
Project-URL: Bug Tracker, https://github.com/bondbox/patroller/issues
Project-URL: Documentation, https://github.com/bondbox/patroller/
Keywords: command-line,argparse,argcomplete
Platform: any
Classifier: Programming Language :: Python
Classifier: Programming Language :: Python :: 3
Requires-Python: >=3.8
